Workbook
Name NativeTimeline_Date: #N/A
Name Slicer_Category: #N/A
Name Slicer_Customer_Segment: #N/A
Name Slicer_Region: #N/A

Sheet Dashboard
G6: Total Revenue | I6: Best Region | K6: Top Category | M6: Top Segment
Y7: =Pivot_Analysis!B9 -> 0 | Z7: =Pivot_Analysis!A4 -> North | AA7: =Pivot_Analysis!E4 -> Appliances | AB7: =Pivot_Analysis!A18 -> Basic
Y21: s

Sheet Final_Report
A1: DATA INTELLIGENCE DASHBOARD – FINAL REPORT
A5: Executive Summary
A6: This report analyzes customer transaction data and provides insights into sales performance, customer behavior, product demand, and regional trends. Interactive dashboards, pivot tables, charts, slicers, timelines, and advanced Excel functions were used to derive meaningful business insights.
A9: Key Metrics
A10: Total Revenue | B10: =Dashboard!Y7 -> 0
A11: Best Performing Region | B11: =Dashboard!Z7 -> North
A12: Top Product Category | B12: =Dashboard!AA7 -> Appliances
A13: Top Customer Segment | B13: =Dashboard!AB7 -> Basic
A14: Total Transactions | B14: =COUNTA(Dataset!A:A)-1 -> 250
A15: Total Quantity Sold | B15: =SUM(Dataset!H:H) -> 753

Sheet Pivot_Analysis
A3: Region | B3: Sum of Total_Amount | E3: Category | F3: Sum of Total_Amount
A4: North | B4: 1119.84 | E4: Appliances | F4: 1119.84
A5: Grand Total | B5: 1119.84 | E5: Grand Total | F5: 1119.84
A15: Customer_Segment | B15: Sum of Total_Amount | E15: Date | F15: Sum of Total_Amount
A16: Premium | B16: 179.97 | E16: 2024 | F16: 879.87
A17: Standard | B17: 379.94 | E17: Qtr2 | F17: 439.93
A18: Basic | B18: 559.93 | E18: Qtr3 | F18: 439.94
A19: Grand Total | B19: 1119.84 | E19: 2025 | F19: 239.97
E20: Qtr2 | F20: 239.97
E21: Grand Total | F21: 1119.84

Sheet Dataset
A1: Transaction_ID | B1: Date | C1: Customer_ID | D1: Customer_Name | E1: Product_ID | F1: Product_Name | G1: Category | H1: Quantity | I1: Unit_Price | J1: Payment_Method | K1: Region | L1: Customer_Segment | M1: Customer_Since | N1: Customer_Tenure | O1: Month_End_Date | P1: Total_Amount
A2: TRX0155 | B2: 45393 | C2: CUST023 | D2: Paul Baker | E2: P009 | F2: Monitor | G2: Electronics | H2: 3 | I2: 249.99 | J2: Cash | K2: Central | L2: Basic | M2: 44425 | N2: =DATEDIF(M2,TODAY(),"Y") -> 4 | O2: =EOMONTH(Dataset!B2,0) -> 45412 | P2: 749.97
A3: TRX0023 | B3: 45396 | C3: CUST013 | D3: Joseph Jackson | E3: P009 | F3: Monitor | G3: Electronics | H3: 3 | I3: 249.99 | J3: Credit Card | K3: Central | L3: Premium | M3: 44575 | N3: =DATEDIF(M3,TODAY(),"Y") -> 4 | O3: =EOMONTH(Dataset!B3,0) -> 45412 | P3: 749.97
A4: TRX0139 | B4: 45399 | C4: CUST021 | D4: Kevin Scott | E4: P005 | F4: Blender | G4: Appliances | H4: 3 | I4: 59.99 | J4: PayPal | K4: South | L4: Standard | M4: 45262 | N4: =DATEDIF(M4,TODAY(),"Y") -> 2 | O4: =EOMONTH(Dataset!B4,0) -> 45412 | P4: 179.97
A5: TRX0043 | B5: 45400 | C5: CUST046 | D5: Kathleen Bennett | E5: P005 | F5: Blender | G5: Appliances | H5: 3 | I5: 59.99 | J5: Cash | K5: North | L5: Premium | M5: 45114 | N5: =DATEDIF(M5,TODAY(),"Y") -> 2 | O5: =EOMONTH(Dataset!B5,0) -> 45412 | P5: 179.97
A6: TRX0212 | B6: 45400 | C6: CUST003 | D6: Michael Brown | E6: P008 | F6: Bookshelf | G6: Furniture | H6: 5 | I6: 149.99 | J6: Credit Card | K6: North | L6: Premium | M6: 45295 | N6: =DATEDIF(M6,TODAY(),"Y") -> 2 | O6: =EOMONTH(Dataset!B6,0) -> 45412 | P6: 749.95
A7: TRX0092 | B7: 45403 | C7: CUST024 | D7: Dorothy Nelson | E7: P005 | F7: Blender | G7: Appliances | H7: 2 | I7: 59.99 | J7: Cash | K7: West | L7: Standard | M7: 44746 | N7: =DATEDIF(M7,TODAY(),"Y") -> 3 | O7: =EOMONTH(Dataset!B7,0) -> 45412 | P7: 119.98
A8: TRX0193 | B8: 45403 | C8: CUST024 | D8: Dorothy Nelson | E8: P003 | F8: Headphones | G8: Electronics | H8: 5 | I8: 149.99 | J8: Credit Card | K8: Central | L8: Standard | M8: 44418 | N8: =DATEDIF(M8,TODAY(),"Y") -> 4 | O8: =EOMONTH(Dataset!B8,0) -> 45412 | P8: 749.95
A9: TRX0240 | B9: 45403 | C9: CUST017 | D9: Charles Allen | E9: P005 | F9: Blender | G9: Appliances | H9: 3 | I9: 59.99 | J9: Debit Card | K9: South | L9: Basic | M9: 45007 | N9: =DATEDIF(M9,TODAY(),"Y") -> 3 | O9: =EOMONTH(Dataset!B9,0) -> 45412 | P9: 179.97
A10: TRX0135 | B10: 45405 | C10: CUST009 | D10: Robert Thomas | E10: P001 | F10: Laptop | G10: Electronics | H10: 3 | I10: 899.99 | J10: PayPal | K10: East | L10: Standard | M10: 45299 | N10: =DATEDIF(M10,TODAY(),"Y") -> 2 | O10: =EOMONTH(Dataset!B10,0) -> 45412 | P10: 2699.97
A11: TRX0185 | B11: 45408 | C11: CUST026 | D11: Karen Hill | E11: P005 | F11: Blender | G11: Appliances | H11: 3 | I11: 59.99 | J11: Cash | K11: West | L11: Premium | M11: 45207 | N11: =DATEDIF(M11,TODAY(),"Y") -> 2 | O11: =EOMONTH(Dataset!B11,0) -> 45412 | P11: 179.97
A12: TRX0138 | B12: 45408 | C12: CUST022 | D12: Susan Green | E12: P008 | F12: Bookshelf | G12: Furniture | H12: 1 | I12: 149.99 | J12: Credit Card | K12: West | L12: Standard | M12: 45103 | N12: =DATEDIF(M12,TODAY(),"Y") -> 2 | O12: =EOMONTH(Dataset!B12,0) -> 45412 | P12: 149.99
A13: TRX0209 | B13: 45408 | C13: CUST046 | D13: Kathleen Bennett | E13: P008 | F13: Bookshelf | G13: Furniture | H13: 5 | I13: 149.99 | J13: Debit Card | K13: North | L13: Basic | M13: 44830 | N13: =DATEDIF(M13,TODAY(),"Y") -> 3 | O13: =EOMONTH(Dataset!B13,0) -> 45412 | P13: 749.95
... A251: TRX0064 | B251: 45758 | C251: CUST031 | D251: Steven Turner | E251: P010 | F251: Keyboard | G251: Electronics | H251: 3 | I251: 89.99 | J251: Debit Card | K251: North | L251: Premium | M251: 44878 | N251: =DATEDIF(M251,TODAY(),"Y") -> 3 | O251: =EOMONTH(Dataset!B251,0) -> 45777 | P251: 269.97

Sheet Compare_Lists
A1: Premium Customers | D1: North Region Customers | G1: Common Customers
A2: {=_xlfn.UNIQUE(_xlfn._xlws.FILTER(Dataset!D:D,Dataset!L:L="Premium"))} -> Joseph Jackson | D2: {=_xlfn.UNIQUE(_xlfn._xlws.FILTER(Dataset!D:D,Dataset!K:K="North"))} -> Kathleen Bennett | G2: {=_xlfn._xlws.FILTER(_xlfn.ANCHORARRAY(A2),COUNTIF(_xlfn.ANCHORARRAY(D2),_xlfn.ANCHORARRAY(A2))>0)} -> Kathleen Bennett
A3: Kathleen Bennett | D3: Michael Brown | G3: Michael Brown
A4: Michael Brown | D4: Peter Richardson | G4: Karen Hill
A5: Karen Hill | D5: Dennis Gray | G5: Peter Richardson
A6: Peter Richardson | D6: George Adams | G6: Mark Carter
A7: Mark Carter | D7: Mark Carter | G7: Virginia Sanders
A8: Virginia Sanders | D8: Maria Garcia | G8: Patricia Moore
A9: Linda Martin | D9: Virginia Sanders | G9: Steven Turner
A10: Patricia Moore | D10: Cynthia Price | G10: Harry Morgan
A11: Emma Wilson | D11: Patricia Moore | G11: Betty Campbell
A12: Kevin Scott | D12: Steven Turner | G12: Barbara Young
A13: Steven Turner | D13: Daniel King | G13: Frank Torres
A14: Harry Morgan | D14: Charles Allen | G14: David Martinez
... A27: Dorothy Nelson | D27: Dorothy Nelson | G27: Sharon Butler
A28: Daniel King | D28: Arthur Edwards
A29: Elizabeth Hall | D29: Michelle Rogers
A30: Maria Garcia | D30: Helen Roberts
A31: Charles Allen | D31: Harry Morgan
A32: William White | D32: Sharon Butler
A33: Nancy Collins
A34: James Johnson
A35: Robert Thomas
A36: Michelle Rogers
A37: Douglas Watson
A38: Ruth Brooks
A39: Richard Lee
A40: Arthur Edwards
A41: Dennis Gray
A42: Sharon Butler

Sheet Abbreviation_Text
A1: {=_xlfn.UNIQUE(Dataset!D:D)} -> Customer_Name | B1: Abbreviation
A2: Paul Baker | B2: =LEFT(A2,1)&MID(A2,FIND(" ",A2)+1,1) -> PB
A3: Joseph Jackson | B3: =LEFT(A3,1)&MID(A3,FIND(" ",A3)+1,1) -> JJ
A4: Kevin Scott | B4: =LEFT(A4,1)&MID(A4,FIND(" ",A4)+1,1) -> KS
A5: Kathleen Bennett | B5: =LEFT(A5,1)&MID(A5,FIND(" ",A5)+1,1) -> KB
A6: Michael Brown | B6: =LEFT(A6,1)&MID(A6,FIND(" ",A6)+1,1) -> MB
A7: Dorothy Nelson | B7: =LEFT(A7,1)&MID(A7,FIND(" ",A7)+1,1) -> DN
A8: Charles Allen | B8: =LEFT(A8,1)&MID(A8,FIND(" ",A8)+1,1) -> CA
A9: Robert Thomas | B9: =LEFT(A9,1)&MID(A9,FIND(" ",A9)+1,1) -> RT
A10: Karen Hill | B10: =LEFT(A10,1)&MID(A10,FIND(" ",A10)+1,1) -> KH
A11: Susan Green | B11: =LEFT(A11,1)&MID(A11,FIND(" ",A11)+1,1) -> SG
A12: Peter Richardson | B12: =LEFT(A12,1)&MID(A12,FIND(" ",A12)+1,1) -> PR
A13: Dennis Gray | B13: =LEFT(A13,1)&MID(A13,FIND(" ",A13)+1,1) -> DG
... A51: John Smith | B51: =LEFT(A51,1)&MID(A51,FIND(" ",A51)+1,1) -> JS
A52: 0 | B52: =LEFT(A52,1)&MID(A52,FIND(" ",A52)+1,1) -> #VALUE!

Sheet Scenario Summary
B2: Scenario Summary
D3: Current Values: | E3: Best case | F3: Normal Case | G3: Worst Case
E4: Created by Lenovo on 29-05-2026 | F4: Created by Lenovo on 29-05-2026 | G4: Created by Lenovo on 29-05-2026
B5: Changing Cells:
C6: $B$12 | D6: 10 | E6: 12 | F6: 10 | G6: 8
C7: $B$13 | D7: 899.99 | E7: 999.99 | F7: 899.99 | G7: 799.99
B8: Result Cells:
C9: $B$18
B10: Notes: Current Values column represents values of changing cells at
B11: time Scenario Summary Report was created. Changing cells for each
B12: scenario are highlighted in gray.

Sheet What_If_Analysis
A1: Goal Seek
A2: Product | B2: Laptop
A3: Quantity | B3: 55.556173
A4: Unit Price | B4: 899.99
A5: Target Revenue | B5: =B3*B4 -> 50000
A11: A | B11: B
A12: Quantity | B12: 10
A13: Unit Price | B13: 899.99
A14: Revenue | B14: =B12*B13 -> 8999.9

Sheet Analysis
A2: Today's Date | B2: Current Date & Time | C2: Month_End_Date
A3: =TODAY() -> 46172 | B3: =NOW() -> 46172.523 | C3: =EOMONTH(Dataset!B2,0) -> 45412

Sheet Regression_Analysis
A1: SUMMARY OUTPUT
A3: Regression Statistics
A4: Multiple R | B4: 0.45808036
A5: R Square | B5: 0.20983762
A6: Adjusted R Square | B6: 0.20665148
A7: Standard Error | B7: 919.60715
A8: Observations | B8: 250
A10: ANOVA
B11: df | C11: SS | D11: MS | E11: F | F11: Significance F
A12: Regression | B12: 1 | C12: 55695917 | D12: 55695917 | E12: 65.859537 | F12: 2.2586479e-14
A13: Residual | B13: 248 | C13: 2.0972797e+08 | D13: 845677.32
A14: Total | B14: 249 | C14: 2.6542389e+08
B16: Coefficients | C16: Standard Error | D16: t Stat | E16: P-value | F16: Lower 95% | G16: Upper 95% | H16: Lower 95.0% | I16: Upper 95.0%
A17: Intercept | B17: -148.85465 | C17: 143.61334 | D17: -1.0364959 | E17: 0.3009804 | F17: -431.712 | G17: 134.0027 | H17: -431.712 | I17: 134.0027
A18: Quantity | B18: 353.793 | C18: 43.595323 | D18: 8.1153889 | E18: 2.2586479e-14 | F18: 267.92872 | G18: 439.65729 | H18: 267.92872 | I18: 439.65729

Sheet Timestamp_Demo
A1: Entry | B1: Timestamp
A2: Hello | B2: =IF(A2<>"",IF(B2="",NOW(),B2),"") -> 46171.745
A3: customer Added | B3: =IF(A2<>"",IF(B2="",NOW(),B2),"") -> 46171.745
A4: New order | B4: =IF(A2<>"",IF(B2="",NOW(),B2),"") -> 46171.745

Sheet Electronics_Filter
A1: Electronic's Category Product's
A2: {=_xlfn.VSTACK(Dataset!A1:N1,_xlfn._xlws.FILTER(Dataset!A2:N251,Dataset!G2:G251="Electronics"))} -> #NAME? | B2: #NAME? | C2: #NAME? | D2: #NAME? | E2: #NAME? | F2: #NAME? | G2: #NAME? | H2: #NAME? | I2: #NAME? | J2: #NAME? | K2: #NAME? | L2: #NAME? | M2: #NAME? | N2: #NAME? | P2: {=_xlfn._xlws.FILTER(Dataset!A:N,Dataset!L:L="Premium")} -> #NAME? | Q2: #NAME? | R2: #NAME? | S2: #NAME? | T2: #NAME? | U2: #NAME? | V2: #NAME? | W2: #NAME? | X2: #NAME? | Y2: #NAME? | Z2: #NAME? | AA2: #NAME? | AB2: #NAME? | AC2: #NAME?
A3: #NAME? | B3: #NAME? | C3: #NAME? | D3: #NAME? | E3: #NAME? | F3: #NAME? | G3: #NAME? | H3: #NAME? | I3: #NAME? | J3: #NAME? | K3: #NAME? | L3: #NAME? | M3: #NAME? | N3: #NAME? | P3: #NAME? | Q3: #NAME? | R3: #NAME? | S3: #NAME? | T3: #NAME? | U3: #NAME? | V3: #NAME? | W3: #NAME? | X3: #NAME? | Y3: #NAME? | Z3: #NAME? | AA3: #NAME? | AB3: #NAME? | AC3: #NAME?
A4: #NAME? | B4: #NAME? | C4: #NAME? | D4: #NAME? | E4: #NAME? | F4: #NAME? | G4: #NAME? | H4: #NAME? | I4: #NAME? | J4: #NAME? | K4: #NAME? | L4: #NAME? | M4: #NAME? | N4: #NAME? | P4: #NAME? | Q4: #NAME? | R4: #NAME? | S4: #NAME? | T4: #NAME? | U4: #NAME? | V4: #NAME? | W4: #NAME? | X4: #NAME? | Y4: #NAME? | Z4: #NAME? | AA4: #NAME? | AB4: #NAME? | AC4: #NAME?
A5: #NAME? | B5: #NAME? | C5: #NAME? | D5: #NAME? | E5: #NAME? | F5: #NAME? | G5: #NAME? | H5: #NAME? | I5: #NAME? | J5: #NAME? | K5: #NAME? | L5: #NAME? | M5: #NAME? | N5: #NAME? | P5: #NAME? | Q5: #NAME? | R5: #NAME? | S5: #NAME? | T5: #NAME? | U5: #NAME? | V5: #NAME? | W5: #NAME? | X5: #NAME? | Y5: #NAME? | Z5: #NAME? | AA5: #NAME? | AB5: #NAME? | AC5: #NAME?
A6: #NAME? | B6: #NAME? | C6: #NAME? | D6: #NAME? | E6: #NAME? | F6: #NAME? | G6: #NAME? | H6: #NAME? | I6: #NAME? | J6: #NAME? | K6: #NAME? | L6: #NAME? | M6: #NAME? | N6: #NAME? | P6: #NAME? | Q6: #NAME? | R6: #NAME? | S6: #NAME? | T6: #NAME? | U6: #NAME? | V6: #NAME? | W6: #NAME? | X6: #NAME? | Y6: #NAME? | Z6: #NAME? | AA6: #NAME? | AB6: #NAME? | AC6: #NAME?
A7: #NAME? | B7: #NAME? | C7: #NAME? | D7: #NAME? | E7: #NAME? | F7: #NAME? | G7: #NAME? | H7: #NAME? | I7: #NAME? | J7: #NAME? | K7: #NAME? | L7: #NAME? | M7: #NAME? | N7: #NAME? | P7: #NAME? | Q7: #NAME? | R7: #NAME? | S7: #NAME? | T7: #NAME? | U7: #NAME? | V7: #NAME? | W7: #NAME? | X7: #NAME? | Y7: #NAME? | Z7: #NAME? | AA7: #NAME? | AB7: #NAME? | AC7: #NAME?
A8: #NAME? | B8: #NAME? | C8: #NAME? | D8: #NAME? | E8: #NAME? | F8: #NAME? | G8: #NAME? | H8: #NAME? | I8: #NAME? | J8: #NAME? | K8: #NAME? | L8: #NAME? | M8: #NAME? | N8: #NAME? | P8: #NAME? | Q8: #NAME? | R8: #NAME? | S8: #NAME? | T8: #NAME? | U8: #NAME? | V8: #NAME? | W8: #NAME? | X8: #NAME? | Y8: #NAME? | Z8: #NAME? | AA8: #NAME? | AB8: #NAME? | AC8: #NAME?
A9: #NAME? | B9: #NAME? | C9: #NAME? | D9: #NAME? | E9: #NAME? | F9: #NAME? | G9: #NAME? | H9: #NAME? | I9: #NAME? | J9: #NAME? | K9: #NAME? | L9: #NAME? | M9: #NAME? | N9: #NAME? | P9: #NAME? | Q9: #NAME? | R9: #NAME? | S9: #NAME? | T9: #NAME? | U9: #NAME? | V9: #NAME? | W9: #NAME? | X9: #NAME? | Y9: #NAME? | Z9: #NAME? | AA9: #NAME? | AB9: #NAME? | AC9: #NAME?
A10: #NAME? | B10: #NAME? | C10: #NAME? | D10: #NAME? | E10: #NAME? | F10: #NAME? | G10: #NAME? | H10: #NAME? | I10: #NAME? | J10: #NAME? | K10: #NAME? | L10: #NAME? | M10: #NAME? | N10: #NAME? | P10: #NAME? | Q10: #NAME? | R10: #NAME? | S10: #NAME? | T10: #NAME? | U10: #NAME? | V10: #NAME? | W10: #NAME? | X10: #NAME? | Y10: #NAME? | Z10: #NAME? | AA10: #NAME? | AB10: #NAME? | AC10: #NAME?
A11: #NAME? | B11: #NAME? | C11: #NAME? | D11: #NAME? | E11: #NAME? | F11: #NAME? | G11: #NAME? | H11: #NAME? | I11: #NAME? | J11: #NAME? | K11: #NAME? | L11: #NAME? | M11: #NAME? | N11: #NAME? | P11: #NAME? | Q11: #NAME? | R11: #NAME? | S11: #NAME? | T11: #NAME? | U11: #NAME? | V11: #NAME? | W11: #NAME? | X11: #NAME? | Y11: #NAME? | Z11: #NAME? | AA11: #NAME? | AB11: #NAME? | AC11: #NAME?
A12: #NAME? | B12: #NAME? | C12: #NAME? | D12: #NAME? | E12: #NAME? | F12: #NAME? | G12: #NAME? | H12: #NAME? | I12: #NAME? | J12: #NAME? | K12: #NAME? | L12: #NAME? | M12: #NAME? | N12: #NAME? | P12: #NAME? | Q12: #NAME? | R12: #NAME? | S12: #NAME? | T12: #NAME? | U12: #NAME? | V12: #NAME? | W12: #NAME? | X12: #NAME? | Y12: #NAME? | Z12: #NAME? | AA12: #NAME? | AB12: #NAME? | AC12: #NAME?
A13: #NAME? | B13: #NAME? | C13: #NAME? | D13: #NAME? | E13: #NAME? | F13: #NAME? | G13: #NAME? | H13: #NAME? | I13: #NAME? | J13: #NAME? | K13: #NAME? | L13: #NAME? | M13: #NAME? | N13: #NAME? | P13: #NAME? | Q13: #NAME? | R13: #NAME? | S13: #NAME? | T13: #NAME? | U13: #NAME? | V13: #NAME? | W13: #NAME? | X13: #NAME? | Y13: #NAME? | Z13: #NAME? | AA13: #NAME? | AB13: #NAME? | AC13: #NAME?
A14: #NAME? | B14: #NAME? | C14: #NAME? | D14: #NAME? | E14: #NAME? | F14: #NAME? | G14: #NAME? | H14: #NAME? | I14: #NAME? | J14: #NAME? | K14: #NAME? | L14: #NAME? | M14: #NAME? | N14: #NAME? | P14: #NAME? | Q14: #NAME? | R14: #NAME? | S14: #NAME? | T14: #NAME? | U14: #NAME? | V14: #NAME? | W14: #NAME? | X14: #NAME? | Y14: #NAME? | Z14: #NAME? | AA14: #NAME? | AB14: #NAME? | AC14: #NAME?
... A96: #NAME? | B96: #NAME? | C96: #NAME? | D96: #NAME? | E96: #NAME? | F96: #NAME? | G96: #NAME? | H96: #NAME? | I96: #NAME? | J96: #NAME? | K96: #NAME? | L96: #NAME? | M96: #NAME? | N96: #NAME? | P96: #NAME? | Q96: #NAME? | R96: #NAME? | S96: #NAME? | T96: #NAME? | U96: #NAME? | V96: #NAME? | W96: #NAME? | X96: #NAME? | Y96: #NAME? | Z96: #NAME? | AA96: #NAME? | AB96: #NAME? | AC96: #NAME?
A97: #NAME? | B97: #NAME? | C97: #NAME? | D97: #NAME? | E97: #NAME? | F97: #NAME? | G97: #NAME? | H97: #NAME? | I97: #NAME? | J97: #NAME? | K97: #NAME? | L97: #NAME? | M97: #NAME? | N97: #NAME?
A98: #NAME? | B98: #NAME? | C98: #NAME? | D98: #NAME? | E98: #NAME? | F98: #NAME? | G98: #NAME? | H98: #NAME? | I98: #NAME? | J98: #NAME? | K98: #NAME? | L98: #NAME? | M98: #NAME? | N98: #NAME?
A99: #NAME? | B99: #NAME? | C99: #NAME? | D99: #NAME? | E99: #NAME? | F99: #NAME? | G99: #NAME? | H99: #NAME? | I99: #NAME? | J99: #NAME? | K99: #NAME? | L99: #NAME? | M99: #NAME? | N99: #NAME?
A100: #NAME? | B100: #NAME? | C100: #NAME? | D100: #NAME? | E100: #NAME? | F100: #NAME? | G100: #NAME? | H100: #NAME? | I100: #NAME? | J100: #NAME? | K100: #NAME? | L100: #NAME? | M100: #NAME? | N100: #NAME?
A101: #NAME? | B101: #NAME? | C101: #NAME? | D101: #NAME? | E101: #NAME? | F101: #NAME? | G101: #NAME? | H101: #NAME? | I101: #NAME? | J101: #NAME? | K101: #NAME? | L101: #NAME? | M101: #NAME? | N101: #NAME?
A102: #NAME? | B102: #NAME? | C102: #NAME? | D102: #NAME? | E102: #NAME? | F102: #NAME? | G102: #NAME? | H102: #NAME? | I102: #NAME? | J102: #NAME? | K102: #NAME? | L102: #NAME? | M102: #NAME? | N102: #NAME?
A103: #NAME? | B103: #NAME? | C103: #NAME? | D103: #NAME? | E103: #NAME? | F103: #NAME? | G103: #NAME? | H103: #NAME? | I103: #NAME? | J103: #NAME? | K103: #NAME? | L103: #NAME? | M103: #NAME? | N103: #NAME?
A104: #NAME? | B104: #NAME? | C104: #NAME? | D104: #NAME? | E104: #NAME? | F104: #NAME? | G104: #NAME? | H104: #NAME? | I104: #NAME? | J104: #NAME? | K104: #NAME? | L104: #NAME? | M104: #NAME? | N104: #NAME?
A105: #NAME? | B105: #NAME? | C105: #NAME? | D105: #NAME? | E105: #NAME? | F105: #NAME? | G105: #NAME? | H105: #NAME? | I105: #NAME? | J105: #NAME? | K105: #NAME? | L105: #NAME? | M105: #NAME? | N105: #NAME?
A106: #NAME? | B106: #NAME? | C106: #NAME? | D106: #NAME? | E106: #NAME? | F106: #NAME? | G106: #NAME? | H106: #NAME? | I106: #NAME? | J106: #NAME? | K106: #NAME? | L106: #NAME? | M106: #NAME? | N106: #NAME?
A107: #NAME? | B107: #NAME? | C107: #NAME? | D107: #NAME? | E107: #NAME? | F107: #NAME? | G107: #NAME? | H107: #NAME? | I107: #NAME? | J107: #NAME? | K107: #NAME? | L107: #NAME? | M107: #NAME? | N107: #NAME?
A108: #NAME? | B108: #NAME? | C108: #NAME? | D108: #NAME? | E108: #NAME? | F108: #NAME? | G108: #NAME? | H108: #NAME? | I108: #NAME? | J108: #NAME? | K108: #NAME? | L108: #NAME? | M108: #NAME? | N108: #NAME?
... A133: #NAME? | B133: #NAME? | C133: #NAME? | D133: #NAME? | E133: #NAME? | F133: #NAME? | G133: #NAME? | H133: #NAME? | I133: #NAME? | J133: #NAME? | K133: #NAME? | L133: #NAME? | M133: #NAME? | N133: #NAME?

Sheet Premium_Customer's_Filter
A1: Premium Customers
A2: {=_xlfn.VSTACK(Dataset!A1:N1,_xlfn._xlws.FILTER(Dataset!A2:N251,Dataset!L2:L251="Premium"))} -> #NAME? | B2: #NAME? | C2: #NAME? | D2: #NAME? | E2: #NAME? | F2: #NAME? | G2: #NAME? | H2: #NAME? | I2: #NAME? | J2: #NAME? | K2: #NAME? | L2: #NAME? | M2: #NAME? | N2: #NAME?
A3: #NAME? | B3: #NAME? | C3: #NAME? | D3: #NAME? | E3: #NAME? | F3: #NAME? | G3: #NAME? | H3: #NAME? | I3: #NAME? | J3: #NAME? | K3: #NAME? | L3: #NAME? | M3: #NAME? | N3: #NAME?
A4: #NAME? | B4: #NAME? | C4: #NAME? | D4: #NAME? | E4: #NAME? | F4: #NAME? | G4: #NAME? | H4: #NAME? | I4: #NAME? | J4: #NAME? | K4: #NAME? | L4: #NAME? | M4: #NAME? | N4: #NAME?
A5: #NAME? | B5: #NAME? | C5: #NAME? | D5: #NAME? | E5: #NAME? | F5: #NAME? | G5: #NAME? | H5: #NAME? | I5: #NAME? | J5: #NAME? | K5: #NAME? | L5: #NAME? | M5: #NAME? | N5: #NAME?
A6: #NAME? | B6: #NAME? | C6: #NAME? | D6: #NAME? | E6: #NAME? | F6: #NAME? | G6: #NAME? | H6: #NAME? | I6: #NAME? | J6: #NAME? | K6: #NAME? | L6: #NAME? | M6: #NAME? | N6: #NAME?
A7: #NAME? | B7: #NAME? | C7: #NAME? | D7: #NAME? | E7: #NAME? | F7: #NAME? | G7: #NAME? | H7: #NAME? | I7: #NAME? | J7: #NAME? | K7: #NAME? | L7: #NAME? | M7: #NAME? | N7: #NAME?
A8: #NAME? | B8: #NAME? | C8: #NAME? | D8: #NAME? | E8: #NAME? | F8: #NAME? | G8: #NAME? | H8: #NAME? | I8: #NAME? | J8: #NAME? | K8: #NAME? | L8: #NAME? | M8: #NAME? | N8: #NAME?
A9: #NAME? | B9: #NAME? | C9: #NAME? | D9: #NAME? | E9: #NAME? | F9: #NAME? | G9: #NAME? | H9: #NAME? | I9: #NAME? | J9: #NAME? | K9: #NAME? | L9: #NAME? | M9: #NAME? | N9: #NAME?
A10: #NAME? | B10: #NAME? | C10: #NAME? | D10: #NAME? | E10: #NAME? | F10: #NAME? | G10: #NAME? | H10: #NAME? | I10: #NAME? | J10: #NAME? | K10: #NAME? | L10: #NAME? | M10: #NAME? | N10: #NAME?
A11: #NAME? | B11: #NAME? | C11: #NAME? | D11: #NAME? | E11: #NAME? | F11: #NAME? | G11: #NAME? | H11: #NAME? | I11: #NAME? | J11: #NAME? | K11: #NAME? | L11: #NAME? | M11: #NAME? | N11: #NAME?
A12: #NAME? | B12: #NAME? | C12: #NAME? | D12: #NAME? | E12: #NAME? | F12: #NAME? | G12: #NAME? | H12: #NAME? | I12: #NAME? | J12: #NAME? | K12: #NAME? | L12: #NAME? | M12: #NAME? | N12: #NAME?
A13: #NAME? | B13: #NAME? | C13: #NAME? | D13: #NAME? | E13: #NAME? | F13: #NAME? | G13: #NAME? | H13: #NAME? | I13: #NAME? | J13: #NAME? | K13: #NAME? | L13: #NAME? | M13: #NAME? | N13: #NAME?
A14: #NAME? | B14: #NAME? | C14: #NAME? | D14: #NAME? | E14: #NAME? | F14: #NAME? | G14: #NAME? | H14: #NAME? | I14: #NAME? | J14: #NAME? | K14: #NAME? | L14: #NAME? | M14: #NAME? | N14: #NAME?
... A97: #NAME? | B97: #NAME? | C97: #NAME? | D97: #NAME? | E97: #NAME? | F97: #NAME? | G97: #NAME? | H97: #NAME? | I97: #NAME? | J97: #NAME? | K97: #NAME? | L97: #NAME? | M97: #NAME? | N97: #NAME?

Sheet North_Region_Filter
A1: North Region Customer's
A2: {=_xlfn.VSTACK(Dataset!A1:N1,_xlfn._xlws.FILTER(Dataset!A2:N251,Dataset!K2:K251="North"))} -> #NAME? | B2: #NAME? | C2: #NAME? | D2: #NAME? | E2: #NAME? | F2: #NAME? | G2: #NAME? | H2: #NAME? | I2: #NAME? | J2: #NAME? | K2: #NAME? | L2: #NAME? | M2: #NAME? | N2: #NAME?
A3: #NAME? | B3: #NAME? | C3: #NAME? | D3: #NAME? | E3: #NAME? | F3: #NAME? | G3: #NAME? | H3: #NAME? | I3: #NAME? | J3: #NAME? | K3: #NAME? | L3: #NAME? | M3: #NAME? | N3: #NAME?
A4: #NAME? | B4: #NAME? | C4: #NAME? | D4: #NAME? | E4: #NAME? | F4: #NAME? | G4: #NAME? | H4: #NAME? | I4: #NAME? | J4: #NAME? | K4: #NAME? | L4: #NAME? | M4: #NAME? | N4: #NAME?
A5: #NAME? | B5: #NAME? | C5: #NAME? | D5: #NAME? | E5: #NAME? | F5: #NAME? | G5: #NAME? | H5: #NAME? | I5: #NAME? | J5: #NAME? | K5: #NAME? | L5: #NAME? | M5: #NAME? | N5: #NAME?
A6: #NAME? | B6: #NAME? | C6: #NAME? | D6: #NAME? | E6: #NAME? | F6: #NAME? | G6: #NAME? | H6: #NAME? | I6: #NAME? | J6: #NAME? | K6: #NAME? | L6: #NAME? | M6: #NAME? | N6: #NAME?
A7: #NAME? | B7: #NAME? | C7: #NAME? | D7: #NAME? | E7: #NAME? | F7: #NAME? | G7: #NAME? | H7: #NAME? | I7: #NAME? | J7: #NAME? | K7: #NAME? | L7: #NAME? | M7: #NAME? | N7: #NAME?
A8: #NAME? | B8: #NAME? | C8: #NAME? | D8: #NAME? | E8: #NAME? | F8: #NAME? | G8: #NAME? | H8: #NAME? | I8: #NAME? | J8: #NAME? | K8: #NAME? | L8: #NAME? | M8: #NAME? | N8: #NAME?
A9: #NAME? | B9: #NAME? | C9: #NAME? | D9: #NAME? | E9: #NAME? | F9: #NAME? | G9: #NAME? | H9: #NAME? | I9: #NAME? | J9: #NAME? | K9: #NAME? | L9: #NAME? | M9: #NAME? | N9: #NAME?
A10: #NAME? | B10: #NAME? | C10: #NAME? | D10: #NAME? | E10: #NAME? | F10: #NAME? | G10: #NAME? | H10: #NAME? | I10: #NAME? | J10: #NAME? | K10: #NAME? | L10: #NAME? | M10: #NAME? | N10: #NAME?
A11: #NAME? | B11: #NAME? | C11: #NAME? | D11: #NAME? | E11: #NAME? | F11: #NAME? | G11: #NAME? | H11: #NAME? | I11: #NAME? | J11: #NAME? | K11: #NAME? | L11: #NAME? | M11: #NAME? | N11: #NAME?
A12: #NAME? | B12: #NAME? | C12: #NAME? | D12: #NAME? | E12: #NAME? | F12: #NAME? | G12: #NAME? | H12: #NAME? | I12: #NAME? | J12: #NAME? | K12: #NAME? | L12: #NAME? | M12: #NAME? | N12: #NAME?
A13: #NAME? | B13: #NAME? | C13: #NAME? | D13: #NAME? | E13: #NAME? | F13: #NAME? | G13: #NAME? | H13: #NAME? | I13: #NAME? | J13: #NAME? | K13: #NAME? | L13: #NAME? | M13: #NAME? | N13: #NAME?
A14: #NAME? | B14: #NAME? | C14: #NAME? | D14: #NAME? | E14: #NAME? | F14: #NAME? | G14: #NAME? | H14: #NAME? | I14: #NAME? | J14: #NAME? | K14: #NAME? | L14: #NAME? | M14: #NAME? | N14: #NAME?
... A61: #NAME? | B61: #NAME? | C61: #NAME? | D61: #NAME? | E61: #NAME? | F61: #NAME? | G61: #NAME? | H61: #NAME? | I61: #NAME? | J61: #NAME? | K61: #NAME? | L61: #NAME? | M61: #NAME? | N61: #NAME?

Sheet High_Value_Customers
A1: Customer Name | B1: Total Revenue
A2: {=_xlfn._xlws.SORT(_xlfn.UNIQUE(Dataset!D2:D251))} -> Arthur Edwards | B2: =SUMIFS(Dataset!P:P,Dataset!D:D,A2) -> 1559.94
A3: Barbara Young | B3: =SUMIFS(Dataset!P:P,Dataset!D:D,A3) -> 10649.8
A4: Betty Campbell | B4: =SUMIFS(Dataset!P:P,Dataset!D:D,A4) -> 5649.84
A5: Carol Evans | B5: =SUMIFS(Dataset!P:P,Dataset!D:D,A5) -> 1149.93
A6: Charles Allen | B6: =SUMIFS(Dataset!P:P,Dataset!D:D,A6) -> 5089.73
A7: Cynthia Price | B7: =SUMIFS(Dataset!P:P,Dataset!D:D,A7) -> 3769.83
A8: Daniel King | B8: =SUMIFS(Dataset!P:P,Dataset!D:D,A8) -> 7309.8
A9: David Martinez | B9: =SUMIFS(Dataset!P:P,Dataset!D:D,A9) -> 1809.84
A10: Dennis Gray | B10: =SUMIFS(Dataset!P:P,Dataset!D:D,A10) -> 479.92
A11: Dorothy Nelson | B11: =SUMIFS(Dataset!P:P,Dataset!D:D,A11) -> 8269.79
A12: Douglas Watson | B12: =SUMIFS(Dataset!P:P,Dataset!D:D,A12) -> 4829.89
A13: Edward Mitchell | B13: =SUMIFS(Dataset!P:P,Dataset!D:D,A13) -> 11919.77
A14: Elizabeth Hall | B14: =SUMIFS(Dataset!P:P,Dataset!D:D,A14) -> 3649.86
... A51: William White | B51: =SUMIFS(Dataset!P:P,Dataset!D:D,A51) -> 4749.91

Sheet Most_Frequent_Product
A1: Product Name | B1: Frequency
A2: {=_xlfn._xlws.SORT(_xlfn.UNIQUE(Dataset!F2:F251))} -> Blender | B2: =COUNTIF(Dataset!F:F,A2) -> 29
A3: Bookshelf | B3: =COUNTIF(Dataset!F:F,A3) -> 35
A4: Coffee Maker | B4: =COUNTIF(Dataset!F:F,A4) -> 14
A5: Desk | B5: =COUNTIF(Dataset!F:F,A5) -> 26
A6: Headphones | B6: =COUNTIF(Dataset!F:F,A6) -> 16
A7: Keyboard | B7: =COUNTIF(Dataset!F:F,A7) -> 34
A8: Laptop | B8: =COUNTIF(Dataset!F:F,A8) -> 24
A9: Monitor | B9: =COUNTIF(Dataset!F:F,A9) -> 26
A10: Office Chair | B10: =COUNTIF(Dataset!F:F,A10) -> 15
A11: Smartphone | B11: =COUNTIF(Dataset!F:F,A11) -> 31
